[{"name":"Aang","totalwords":1797},{"name":"Appa","totalwords":3},{"name":"Azula","totalwords":232},{"name":"Azulon","totalwords":3},{"name":"Bato","totalwords":38},{"name":"Bumi","totalwords":71},{"name":"Cabbage merchant","totalwords":7},{"name":"Gyatso","totalwords":19},{"name":"Hakoda","totalwords":77},{"name":"Haru","totalwords":29},{"name":"Iroh","totalwords":337},{"name":"Jeong Jeong","totalwords":32},{"name":"Jet","totalwords":134},{"name":"Kanna","totalwords":10},{"name":"Katara","totalwords":1443},{"name":"Kuruk","totalwords":1},{"name":"Kya","totalwords":6},{"name":"Lion turtle","totalwords":4},{"name":"Long Feng","totalwords":46},{"name":"Longshot","totalwords":1},{"name":"Mai","totalwords":83},{"name":"Momo","totalwords":4},{"name":"Ozai","totalwords":59},{"name":"Pakku","totalwords":37},{"name":"Pathik","totalwords":38},{"name":"Piandao","totalwords":43},{"name":"Pipsqueak","totalwords":9},{"name":"Roku","totalwords":71},{"name":"Smellerbee","totalwords":22},{"name":"Sokka","totalwords":1639},{"name":"Sozin","totalwords":26},{"name":"Suki","totalwords":114},{"name":"The Boulder","totalwords":9},{"name":"The Duke","totalwords":9},{"name":"Toph","totalwords":507},{"name":"Ty Lee","totalwords":66},{"name":"Ursa","totalwords":22},{"name":"Xin Fu","totalwords":27},{"name":"Yangchen","totalwords":4},{"name":"Yue","totalwords":54},{"name":"Zhao","totalwords":107},{"name":"Zuko","totalwords":809}]